pyportal/__init__.py
pyportal/scriptrepo.py
pyportal-1.0.1.dist-info/METADATA
pyportal-1.0.1.dist-info/WHEEL
pyportal-1.0.1.dist-info/top_level.txt
pyportal-1.0.1.dist-info/RECORD
