Metadata-Version: 2.1
Name: pyportal
Version: 1.0.1
Summary: Import Python script from any directory or git commit history.
Home-page: https://github.com/alanyue/pyportal
Author: Alan Yue
Author-email: alanyue@example.com
License: MIT
Keywords: import python scripts git version control
Classifier: Development Status :: 4 - Beta
Classifier: Intended Audience :: Developers
Classifier: License :: OSI Approved :: MIT License
Classifier: Operating System :: OS Independent
Classifier: Programming Language :: Python :: 3
Classifier: Programming Language :: Python :: 3.7
Classifier: Programming Language :: Python :: 3.8
Classifier: Programming Language :: Python :: 3.9
Classifier: Programming Language :: Python :: 3.10
Classifier: Programming Language :: Python :: 3.11
Classifier: Topic :: Software Development :: Libraries :: Python Modules
Requires-Python: >=3.7
